clicktrack/__about__.py
clicktrack/__init__.py
clicktrack/cli.py
clicktrack-0.1.0.dist-info/METADATA
clicktrack-0.1.0.dist-info/WHEEL
clicktrack-0.1.0.dist-info/entry_points.txt
clicktrack-0.1.0.dist-info/licenses/LICENSE.txt
clicktrack-0.1.0.dist-info/RECORD
