Metadata-Version: 2.4
Name: clicktrack
Version: 0.1.0
Summary: Create click tracks in MIDI format.
Project-URL: Documentation, https://github.com/yaph/clicktrack#readme
Project-URL: Issues, https://github.com/yaph/clicktrack/issues
Project-URL: Source, https://github.com/yaph/clicktrack
Author-email: Ramiro Gómez <code@ramiro.org>
License-Expression: MIT
License-File: LICENSE.txt
Keywords: audio,cli,click track,command line,count-in,midi,midi-generator,music
Classifier: Development Status :: 4 - Beta
Classifier: Programming Language :: Python
Classifier: Programming Language :: Python :: 3.10
Classifier: Programming Language :: Python :: 3.11
Classifier: Programming Language :: Python :: 3.12
Classifier: Programming Language :: Python :: Implementation :: CPython
Classifier: Programming Language :: Python :: Implementation :: PyPy
Requires-Python: >=3.10
Requires-Dist: midiutil
